seekout/__init__.py
seekout/alerts/__init__.py
seekout/alerts/sms.py
seekout/drivers/__init__.py
seekout/drivers/selenium.py
seekout/objects/AMD.py
seekout/objects/Nvidia.py
seekout/objects/__init__.py
seekout/objects/product.py
seekout/parsers/__init__.py
seekout/parsers/amazon.py
seekout/parsers/bestbuy.py
seekout/parsers/generic.py
seekout/parsers/newegg.py
seekout/parsers/utils.py
seekout-0.1.3.dist-info/LICENSE.md
seekout-0.1.3.dist-info/WHEEL
seekout-0.1.3.dist-info/METADATA
seekout-0.1.3.dist-info/RECORD
