Metadata-Version: 2.1
Name: seekout
Version: 0.1.3
Summary: Library for parsing web pages
License: MIT
Author: mauza
Author-email: mauza@mauza.net
Requires-Python: >=3.8,<4.0
Classifier: License :: OSI Approved :: MIT License
Classifier: Programming Language :: Python :: 3
Classifier: Programming Language :: Python :: 3.8
Classifier: Programming Language :: Python :: 3.9
Requires-Dist: beautifulsoup4 (>=4.9.3,<5.0.0)
Requires-Dist: python-dotenv (>=0.15.0,<0.16.0)
Requires-Dist: requests (>=2.24.0,<3.0.0)
Requires-Dist: selenium (>=3.141.0,<4.0.0)
